package/__init__.py
package/anticaptcha.py
package/patch.py
package/recaptcha_solver.py
commonutils_whitetail-0.0.2.dist-info/LICENSE
commonutils_whitetail-0.0.2.dist-info/METADATA
commonutils_whitetail-0.0.2.dist-info/WHEEL
commonutils_whitetail-0.0.2.dist-info/top_level.txt
commonutils_whitetail-0.0.2.dist-info/RECORD
