Metadata-Version: 2.1
Name: commonutils-whitetail
Version: 0.0.2
Summary: Common utils
Home-page: https://bitbucket.org/mediblock/lib-web-scrape-utils/
Author: Ankesh Gautam
Author-email: ankesh.gautam@whitetail.in
License: UNKNOWN
Project-URL: Bug Tracker, https://bitbucket.org/mediblock/lib-web-scrape-utils/issues
Platform: UNKNOWN
Classifier: Programming Language :: Python :: 3
Classifier: License :: OSI Approved :: MIT License
Classifier: Operating System :: OS Independent
Requires-Python: >=3.6
License-File: LICENSE
